[
  { "id": 1, "titulo": "Cien años de soledad", "autor": "Gabriel García Márquez", "categoria": "Realismo Mágico", "anio": 1967, "descripcion": "La saga de los Buendía en Macondo.", "imagen": "/images/libros/1.jpg" },
  { "id": 2, "titulo": "1984", "autor": "George Orwell", "categoria": "Distopía", "anio": 1949, "descripcion": "El Gran Hermano todo lo ve.", "imagen": "/images/libros/2.jpg" },
  { "id": 3, "titulo": "El resplandor", "autor": "Stephen King", "categoria": "Misterio y Terror", "anio": 1977, "descripcion": "Aislamiento y locura en el Hotel Overlook.", "imagen": "/images/libros/3.jpg" },
  { "id": 4, "titulo": "Don Quijote de la Mancha", "autor": "Miguel de Cervantes", "categoria": "Ficción Clásica", "anio": 1605, "descripcion": "Las aventuras de un caballero idealista.", "imagen": "/images/libros/4.jpg" },
  { "id": 5, "titulo": "El Alquimista", "autor": "Paulo Coelho", "categoria": "Fantasía y Aventura", "anio": 1988, "descripcion": "Un viaje en busca de la Leyenda Personal.", "imagen": "/images/libros/5.jpg" },
  { "id": 6, "titulo": "Harry Potter y la Piedra Filosofal", "autor": "J.K. Rowling", "categoria": "Fantasía y Aventura", "anio": 1997, "descripcion": "El inicio de la historia del niño mago.", "imagen": "/images/libros/6.jpg" },
  { "id": 7, "titulo": "Crónica de una muerte anunciada", "autor": "Gabriel García Márquez", "categoria": "Realismo Mágico", "anio": 1981, "descripcion": "Un destino trágico que todos conocían.", "imagen": "/images/libros/7.jpg" },
  { "id": 8, "titulo": "Rayuela", "autor": "Julio Cortázar", "categoria": "Ficción Clásica", "anio": 1963, "descripcion": "Un juego literario entre París y Buenos Aires.", "imagen": "/images/libros/8.jpg" },
  { "id": 9, "titulo": "Orgullo y Prejuicio", "autor": "Jane Austen", "categoria": "Ficción Clásica", "anio": 1813, "descripcion": "Lucha de clases y amor en la Inglaterra rural.", "imagen": "/images/libros/9.jpg" },
  { "id": 10, "titulo": "El Gran Gatsby", "autor": "F. Scott Fitzgerald", "categoria": "Ficción Clásica", "anio": 1925, "descripcion": "El sueño americano en los años veinte.", "imagen": "/images/libros/10.jpg" },
  { "id": 11, "titulo": "Sapiens", "autor": "Yuval Noah Harari", "categoria": "No Ficción", "anio": 2011, "descripcion": "Breve historia de la humanidad.", "imagen": "/images/libros/11.jpg" },
  { "id": 12, "titulo": "El nombre de la rosa", "autor": "Umberto Eco", "categoria": "Misterio y Terror", "anio": 1980, "descripcion": "Crímenes en una abadía medieval.", "imagen": "/images/libros/12.jpg" },
  { "id": 13, "titulo": "Pedro Páramo", "autor": "Juan Rulfo", "categoria": "Realismo Mágico", "anio": 1955, "descripcion": "Un viaje al pueblo de los muertos, Comala.", "imagen": "/images/libros/13.jpg" },
  { "id": 14, "titulo": "Los juegos del hambre", "autor": "Suzanne Collins", "categoria": "Distopía", "anio": 2008, "descripcion": "Supervivencia en un futuro distópico.", "imagen": "/images/libros/14.jpg" },
  { "id": 15, "titulo": "Fahrenheit 451", "autor": "Ray Bradbury", "categoria": "Distopía", "anio": 1953, "descripcion": "Un futuro donde los libros están prohibidos.", "imagen": "/images/libros/15.jpg" }
]